wikiscrap/__init__.py
wikiscrap-0.0.1.dist-info/LICENSE.txt
wikiscrap-0.0.1.dist-info/METADATA
wikiscrap-0.0.1.dist-info/WHEEL
wikiscrap-0.0.1.dist-info/top_level.txt
wikiscrap-0.0.1.dist-info/RECORD
